chessbot/__init__.py
chessbot/database.py
chessbot/get_refresh_token.py
chessbot/moves.py
chessbot-0.1.0.dist-info/LICENSE
chessbot-0.1.0.dist-info/METADATA
chessbot-0.1.0.dist-info/WHEEL
chessbot-0.1.0.dist-info/entry_points.txt
chessbot-0.1.0.dist-info/top_level.txt
chessbot-0.1.0.dist-info/RECORD
