Metadata-Version: 2.1
Name: chessbot
Version: 0.1.0
Summary: A Reddit bot for moderating the /r/communitychess subreddit
Author-email: Timothy Harding <tim@timharding.co>
License: Copyright 2024 Timothy Harding
Project-URL: Repository, https://github.com/tim-harding/community_chess
Keywords: reddit,chess
Requires-Python: >=3.12
License-File: LICENSE
Requires-Dist: asyncpraw ~=7.7
Requires-Dist: praw ~=7.7
Requires-Dist: chess ~=1.10
Requires-Dist: cairosvg ~=2.7
Provides-Extra: dev
Requires-Dist: mypy ~=1.8 ; extra == 'dev'
